sipo.v


module sipo (clk,reset,a,shift,out);
input clk;
input reset;
input shift;
input a;
output reg [3:0]out;

reg [3:0]mem;
reg [2:0]counter;

always@(posedge clk) begin

 if(reset) begin
 	counter=3'b000;
 	mem=3'b000;
 	out=1'b0;
 	end

 	
 if(shift)begin  //right shift happening fine
	//mem[3]<=a;	
	if(counter<3'b011) begin
	mem[3]<=a;
	//out<=4'b0000; 
 	mem=mem>>1'b1;
 	counter<=counter+1'b1;
 	out<=4'b0000;
 			end
 	
 	else	 begin
 		counter<=3'b000;
 		out<=mem;
 			end

	end
 	
end
endmodule

single_shift.v
module single_shift(clk,reset,shift,a,y);
input a;
input clk;
input reset;
input shift;
output reg y;



always@(posedge clk) begin

if(reset) begin
	y<=1'b0;
	end 


else
	y<=a;
	
	
end
endmodule

full_adder.v
module full_adder(a,b,cin,sum,cout);
input a;
input b;
input cin;
output sum;
output cout;


assign sum=a^b^cin;
assign cout=(a&b)|(b&cin)|(cin&a);

endmodule

piso.v


//data is getting loaded but not coming out//

module piso (clk,reset,load,shift,d_in,d_out);
input clk;
input reset;
input load;
input shift;
input [3:0] d_in;
output reg d_out;

//integer i;
reg [3:0] mem;
reg[2:0] counter;


///synchronization is the funckin problem
initial begin
counter=3'b000;
end

always@(*) begin
	if(load) begin	//loading is working well	
		mem<=d_in; 
		end 
end


always@(posedge clk) begin
	
		if(shift) begin
		
			if(counter!=3'b011) begin
			//d_out<=mem[0];
			mem=mem>>1'b1; 
			d_out<=mem[0];         //first shift then pull to out
			counter<=counter+1'b1;
				end
		
			else 
				counter<=3'b000;
					
			end
		
end
endmodule

serial_adder.v
// A 4 bit serial adder

`include "full_adder.v"
`include "piso.v"
`include "single_shift.v"
`include "sipo.v"

module serial_adder(clk,load,reset,shift,a,b,sum);
input clk;
input load;
input shift;
input reset;
input [3:0]a;
input [3:0]b;
output [3:0]sum;


wire w1;
wire w2;
wire w3;
wire w4;
wire w5;

//module instantiations
piso p1 (.clk(clk),.reset(reset),.load(load),.shift(shift),.d_in(a),.d_out(w1));
piso p2 (.clk(clk),.reset(reset),.load(load),.shift(shift),.d_in(b),.d_out(w2));
full_adder f1 (.a(w1),.b(w2),.cin(w4),.sum(w5),.cout(w3));
single_shift s1(.clk(clk),.reset(reset),.shift(shift),.a(w3),.y(w4));
sipo sp1 (.clk(clk),.reset(reset),.shift(shift),.a(w5),.out(sum));

endmodule

serial_adder_tb.v

//`include "serial_adder.v"
//test bench in verilog only for simulation level of verification 
module serial_adder_tb();
reg clk;
reg reset;
reg load;
reg shift;
reg [3:0]a;
reg [3:0]b;
wire [3:0]sum;

serial_adder dut(.clk(clk),.reset(reset),.load(load),.shift(shift),.a(a),.b(b),.sum(sum));

initial begin
$dumpfile("output_wave.vcd");
$dumpvars(0,serial_adder_tb);
end

initial begin
clk=1'b0;
reset=1'b1;
load=1'b1;
shift=1'b1;
#5 reset=1'b0;
#20
a=4'b1101;
b=4'b0010;

#500 $finish;
end

always #5 clk=~clk;

endmodule

output_wave.vcd
$date
	Wed May  8 16:46:41 2024
$end
$version
	Icarus Verilog
$end
$timescale
	1s
$end
$scope module serial_adder_tb $end
$var wire 4 ! sum [3:0] $end
$var reg 4 " a [3:0] $end
$var reg 4 # b [3:0] $end
$var reg 1 $ clk $end
$var reg 1 % load $end
$var reg 1 & reset $end
$var reg 1 ' shift $end
$scope module dut $end
$var wire 4 ( a [3:0] $end
$var wire 4 ) b [3:0] $end
$var wire 1 $ clk $end
$var wire 1 % load $end
$var wire 1 & reset $end
$var wire 1 ' shift $end
$var wire 1 * w5 $end
$var wire 1 + w4 $end
$var wire 1 , w3 $end
$var wire 1 - w2 $end
$var wire 1 . w1 $end
$var wire 4 / sum [3:0] $end
$scope module f1 $end
$var wire 1 , cout $end
$var wire 1 * sum $end
$var wire 1 + cin $end
$var wire 1 - b $end
$var wire 1 . a $end
$upscope $end
$scope module p1 $end
$var wire 1 $ clk $end
$var wire 4 0 d_in [3:0] $end
$var wire 1 % load $end
$var wire 1 & reset $end
$var wire 1 ' shift $end
$var reg 3 1 counter [2:0] $end
$var reg 1 . d_out $end
$var reg 4 2 mem [3:0] $end
$upscope $end
$scope module p2 $end
$var wire 1 $ clk $end
$var wire 4 3 d_in [3:0] $end
$var wire 1 % load $end
$var wire 1 & reset $end
$var wire 1 ' shift $end
$var reg 3 4 counter [2:0] $end
$var reg 1 - d_out $end
$var reg 4 5 mem [3:0] $end
$upscope $end
$scope module s1 $end
$var wire 1 , a $end
$var wire 1 $ clk $end
$var wire 1 & reset $end
$var wire 1 ' shift $end
$var reg 1 + y $end
$upscope $end
$scope module sp1 $end
$var wire 1 * a $end
$var wire 1 $ clk $end
$var wire 1 & reset $end
$var wire 1 ' shift $end
$var reg 3 6 counter [2:0] $end
$var reg 4 7 mem [3:0] $end
$var reg 4 8 out [3:0] $end
$upscope $end
$upscope $end
$upscope $end
$enddefinitions $end
#0
$dumpvars
bx 8
bx 7
bx 6
bx 5
b0 4
bx 3
bx 2
b0 1
bx 0
bx /
x.
x-
x,
x+
x*
bx )
bx (
1'
1&
1%
0$
bx #
bx "
bx !
$end
#5
b1 1
b1 4
b0 6
b0xxx 2
b0xxx 5
1$
0&
#10
0$
#15
b0 !
b0 /
b0 8
b1 6
b10 4
b10 1
bx 7
b0xx 5
b0xx 2
1$
#20
0$
#25
b11 1
b11 4
b10 6
b1101 2
b10 5
bx 7
1$
b10 #
b10 )
b10 3
b1101 "
b1101 (
b1101 0
#30
0$
#35
b11 6
b0 4
b0 1
bx 7
1$
#40
0$
#45
b1 1
0.
b1 4
1-
bx !
bx /
bx 8
b0 6
b110 2
b1 5
1$
#50
0$
#55
b0 !
b0 /
b0 8
b1 6
b10 4
0-
b10 1
1.
bx 7
b0 5
b11 2
1$
#60
0$
#65
b11 1
b11 4
b10 6
b1 2
bx 7
1$
#70
0$
#75
b11 6
b0 4
b0 1
bx 7
1$
#80
0$
#85
0,
b1 1
0.
b1 4
bx !
bx /
bx 8
b0 6
b0 2
1$
#90
0$
#95
0*
b0 !
b0 /
b0 8
b1 6
0+
b10 4
b10 1
bx 7
1$
#100
0$
#105
b11 1
b11 4
b10 6
b0xxx 7
1$
#110
0$
#115
b11 6
b0 4
b0 1
b0xx 7
1$
#120
0$
#125
b1 1
b1 4
b0xx !
b0xx /
b0xx 8
b0 6
1$
#130
0$
#135
b0 !
b0 /
b0 8
b1 6
b10 4
b10 1
b0x 7
1$
#140
0$
#145
b11 1
b11 4
b10 6
b0 7
1$
#150
0$
#155
b11 6
b0 4
b0 1
1$
#160
0$
#165
b1 1
b1 4
b0 6
1$
#170
0$
#175
b1 6
b10 4
b10 1
1$
#180
0$
#185
b11 1
b11 4
b10 6
1$
#190
0$
#195
b11 6
b0 4
b0 1
1$
#200
0$
#205
b1 1
b1 4
b0 6
1$
#210
0$
#215
b1 6
b10 4
b10 1
1$
#220
0$
#225
b11 1
b11 4
b10 6
1$
#230
0$
#235
b11 6
b0 4
b0 1
1$
#240
0$
#245
b1 1
b1 4
b0 6
1$
#250
0$
#255
b1 6
b10 4
b10 1
1$
#260
0$
#265
b11 1
b11 4
b10 6
1$
#270
0$
#275
b11 6
b0 4
b0 1
1$
#280
0$
#285
b1 1
b1 4
b0 6
1$
#290
0$
#295
b1 6
b10 4
b10 1
1$
#300
0$
#305
b11 1
b11 4
b10 6
1$
#310
0$
#315
b11 6
b0 4
b0 1
1$
#320
0$
#325
b1 1
b1 4
b0 6
1$
#330
0$
#335
b1 6
b10 4
b10 1
1$
#340
0$
#345
b11 1
b11 4
b10 6
1$
#350
0$
#355
b11 6
b0 4
b0 1
1$
#360
0$
#365
b1 1
b1 4
b0 6
1$
#370
0$
#375
b1 6
b10 4
b10 1
1$
#380
0$
#385
b11 1
b11 4
b10 6
1$
#390
0$
#395
b11 6
b0 4
b0 1
1$
#400
0$
#405
b1 1
b1 4
b0 6
1$
#410
0$
#415
b1 6
b10 4
b10 1
1$
#420
0$
#425
b11 1
b11 4
b10 6
1$
#430
0$
#435
b11 6
b0 4
b0 1
1$
#440
0$
#445
b1 1
b1 4
b0 6
1$
#450
0$
#455
b1 6
b10 4
b10 1
1$
#460
0$
#465
b11 1
b11 4
b10 6
1$
#470
0$
#475
b11 6
b0 4
b0 1
1$
#480
0$
#485
b1 1
b1 4
b0 6
1$
#490
0$
#495
b1 6
b10 4
b10 1
1$
#500
0$
#505
b11 1
b11 4
b10 6
1$
#510
0$
#515
b11 6
b0 4
b0 1
1$
#520
0$
#525
b1 1
b1 4
b0 6
1$
