sipo.v
module sipo (clk,a,shift,out);
input clk;
//input reset;
input shift;
input a;
output reg [3:0]out;

reg [3:0]mem;
reg [2:0]counter;

always@(posedge clk) begin

 /*if(reset) begin
 	counter<=3'b000;
 	end*/

 	
if(shift)begin  //right shift happening fine
	//mem[3]<=a;	
	if(counter<3'b011) begin
	mem[3]<=a;
	//out<=4'b0000; 
 	mem=mem>>1'b1;
 	counter<=counter+1'b1;
 	out<=4'b0000;
 			end
 	
 	else	 begin
 		counter<=3'b000;
 		out<=mem;
 			end

	end
 	
end
endmodule

single_shift.v
module single_shift(clk,shift,a,y);
input a;
input clk;
//input reset;
input shift;
output reg y;



always@(posedge clk) begin

/*if(reset) begin
	y<=1'b0;
	end */

case(shift)
1'b1:y<=a;
1'b0:y<=1'b0;
default:y<=1'b0;
endcase
	
	
end
endmodule

full_adder.v
module full_adder(a,b,cin,sum,cout);
input a;
input b;
input cin;
output sum;
output cout;

assign sum=a^b^cin;
assign cout=(a&b)|(b&cin)|(cin&a);

endmodule

piso.v


//data is getting loaded but not coming out//

module piso (clk,load,shift,d_in,d_out);
input clk;
//input reset;
input load;
input shift;
input [3:0] d_in;
output reg d_out;

//integer i;
reg [3:0] mem=3'b000;
reg[2:0] counter=3'b000;


//write the new code ///synchronization in the funckin problem

always@(*) begin
	if(load) begin	//loading is working well	
		mem<=d_in; 
		end 
end

always@(posedge clk or posedge shift) begin
	
		if(shift) begin
		
			if(counter<3'b011) begin
			mem=mem>>1'b1; 
			d_out<=mem[0];     //first shift then pull to out
			counter<=counter+1'b1;
		end
		
		else 	
			counter<=3'b000;
	
		end
end
endmodule

serial_adder.v
// A 4 bit serial adder

`include "full_adder.v"
`include "piso.v"
`include "single_shift.v"
`include "sipo.v"

module serial_adder(clk,load,shift,a,b,sum);
input clk;
input load;
input shift;
//input reset;
input [3:0]a;
input [3:0]b;
output [3:0]sum;


wire w1;
wire w2;
wire w3;
wire w4;
wire w5;

//module instantiations
piso p1 (.clk(clk),.load(load),.shift(shift),.d_in(a),.d_out(w1));
piso p2 (.clk(clk),.load(load),.shift(shift),.d_in(b),.d_out(w2));
full_adder f1 (.a(w1),.b(w2),.cin(w4),.sum(w5),.cout(w3));
single_shift s1(.clk(clk),.shift(shift),.a(w3),.y(w4));
sipo sp1 (.clk(clk),.shift(shift),.a(w5),.out(sum));

endmodule

serial_adder_tb.v

//`include "serial_adder.v"
//test bench in verilog only for simulation level of verification 
module serial_adder_tb();
reg clk;
//reg reset;
reg load;
reg shift;
reg [3:0]a;
reg [3:0]b;
wire [3:0]sum;

serial_adder dut(.clk(clk),.load(load),.shift(shift),.a(a),.b(b),.sum(sum));

initial begin
$dumpfile("output_wave.vcd");
$dumpvars(0,serial_adder_tb);
end

initial begin
clk=1'b0;
load=1'b1;
shift=1'b1;
a=4'b1100;
b=4'b0111;

#500 $finish;
end

always #5 clk=~clk;

endmodule

output_wave.vcd
$date
	Tue May  7 12:53:15 2024
$end
$version
	Icarus Verilog
$end
$timescale
	1s
$end
$scope module serial_adder_tb $end
$var wire 4 ! sum [3:0] $end
$var reg 4 " a [3:0] $end
$var reg 4 # b [3:0] $end
$var reg 1 $ clk $end
$var reg 1 % load $end
$var reg 1 & shift $end
$scope module dut $end
$var wire 4 ' a [3:0] $end
$var wire 4 ( b [3:0] $end
$var wire 1 $ clk $end
$var wire 1 % load $end
$var wire 1 & shift $end
$var wire 1 ) w5 $end
$var wire 1 * w4 $end
$var wire 1 + w3 $end
$var wire 1 , w2 $end
$var wire 1 - w1 $end
$var wire 4 . sum [3:0] $end
$scope module f1 $end
$var wire 1 + cout $end
$var wire 1 ) sum $end
$var wire 1 * cin $end
$var wire 1 , b $end
$var wire 1 - a $end
$upscope $end
$scope module p1 $end
$var wire 1 $ clk $end
$var wire 4 / d_in [3:0] $end
$var wire 1 % load $end
$var wire 1 & shift $end
$var reg 3 0 counter [2:0] $end
$var reg 1 - d_out $end
$var reg 4 1 mem [3:0] $end
$upscope $end
$scope module p2 $end
$var wire 1 $ clk $end
$var wire 4 2 d_in [3:0] $end
$var wire 1 % load $end
$var wire 1 & shift $end
$var reg 3 3 counter [2:0] $end
$var reg 1 , d_out $end
$var reg 4 4 mem [3:0] $end
$upscope $end
$scope module s1 $end
$var wire 1 + a $end
$var wire 1 $ clk $end
$var wire 1 & shift $end
$var reg 1 * y $end
$upscope $end
$scope module sp1 $end
$var wire 1 ) a $end
$var wire 1 $ clk $end
$var wire 1 & shift $end
$var reg 3 5 counter [2:0] $end
$var reg 4 6 mem [3:0] $end
$var reg 4 7 out [3:0] $end
$upscope $end
$upscope $end
$upscope $end
$enddefinitions $end
#0
$dumpvars
bx 7
bx 6
bx 5
b111 4
b1 3
b111 2
b1100 1
b1 0
b1100 /
bx .
0-
0,
0+
x*
x)
b111 (
b1100 '
1&
1%
0$
b111 #
b1100 "
bx !
$end
#5
1)
b10 3
1,
b10 0
0*
b0 5
b11 4
b110 1
1$
#10
0$
#15
1+
0)
b11 0
1-
b11 3
b0 !
b0 .
b0 7
b1 5
b11 1
b1 4
b1xxx 6
1$
#20
0$
#25
1)
b0 3
b0 0
1*
b10 5
b1xx 6
1$
#30
0$
#35
0)
b1 0
b1 3
0,
b11 5
b1 1
b0 4
b101x 6
1$
#40
0$
#45
0+
1)
b10 3
b10 0
0-
b101x !
b101x .
b101x 7
b0 5
b0 1
1$
#50
0$
#55
0)
b11 0
b11 3
b0 !
b0 .
b0 7
b1 5
0*
b1101 6
1$
#60
0$
#65
b0 3
b0 0
b10 5
b110 6
1$
#70
0$
#75
b1 0
b1 3
b11 5
b11 6
1$
#80
0$
#85
b10 3
b10 0
b11 !
b11 .
b11 7
b0 5
1$
#90
0$
#95
b11 0
b11 3
b0 !
b0 .
b0 7
b1 5
b1 6
1$
#100
0$
#105
b0 3
b0 0
b10 5
b0 6
1$
#110
0$
#115
b1 0
b1 3
b11 5
1$
#120
0$
#125
b10 3
b10 0
b0 5
1$
#130
0$
#135
b11 0
b11 3
b1 5
1$
#140
0$
#145
b0 3
b0 0
b10 5
1$
#150
0$
#155
b1 0
b1 3
b11 5
1$
#160
0$
#165
b10 3
b10 0
b0 5
1$
#170
0$
#175
b11 0
b11 3
b1 5
1$
#180
0$
#185
b0 3
b0 0
b10 5
1$
#190
0$
#195
b1 0
b1 3
b11 5
1$
#200
0$
#205
b10 3
b10 0
b0 5
1$
#210
0$
#215
b11 0
b11 3
b1 5
1$
#220
0$
#225
b0 3
b0 0
b10 5
1$
#230
0$
#235
b1 0
b1 3
b11 5
1$
#240
0$
#245
b10 3
b10 0
b0 5
1$
#250
0$
#255
b11 0
b11 3
b1 5
1$
#260
0$
#265
b0 3
b0 0
b10 5
1$
#270
0$
#275
b1 0
b1 3
b11 5
1$
#280
0$
#285
b10 3
b10 0
b0 5
1$
#290
0$
#295
b11 0
b11 3
b1 5
1$
#300
0$
#305
b0 3
b0 0
b10 5
1$
#310
0$
#315
b1 0
b1 3
b11 5
1$
#320
0$
#325
b10 3
b10 0
b0 5
1$
#330
0$
#335
b11 0
b11 3
b1 5
1$
#340
0$
#345
b0 3
b0 0
b10 5
1$
#350
0$
#355
b1 0
b1 3
b11 5
1$
#360
0$
#365
b10 3
b10 0
b0 5
1$
#370
0$
#375
b11 0
b11 3
b1 5
1$
#380
0$
#385
b0 3
b0 0
b10 5
1$
#390
0$
#395
b1 0
b1 3
b11 5
1$
#400
0$
#405
b10 3
b10 0
b0 5
1$
#410
0$
#415
b11 0
b11 3
b1 5
1$
#420
0$
#425
b0 3
b0 0
b10 5
1$
#430
0$
#435
b1 0
b1 3
b11 5
1$
#440
0$
#445
b10 3
b10 0
b0 5
1$
#450
0$
#455
b11 0
b11 3
b1 5
1$
#460
0$
#465
b0 3
b0 0
b10 5
1$
#470
0$
#475
b1 0
b1 3
b11 5
1$
#480
0$
#485
b10 3
b10 0
b0 5
1$
#490
0$
#495
b11 0
b11 3
b1 5
1$
