sipo.v


module sipo (clk,reset,a,shift,out);
input clk;
input reset;
input shift;
input a;
output reg [3:0]out;

reg [3:0]mem;
reg [2:0]counter;

	
always@(posedge clk) begin
	
 if(reset) begin
 	mem=4'b0000;
 	end
 	
 if(!reset) begin
 	
 		if(shift)begin
 				  //right shift happening fine		
			if(counter<3'b100) begin
			mem[3]<=a;
 			mem=mem>>1'b1;
 			counter<=counter+1'b1;
 			out<=4'b0000;
 			//out<=mem;
 				end
 				
 			else	 begin
 			//out=mem;
 			counter<=3'b000;
 			out<=mem;
 			end

	end
end
	
	
 	
end
endmodule

single_shift.v
module single_shift(clk,reset,load,shift,a,y);
input a;
input clk;
input reset;
input shift;
input load;
output reg y;

reg [2:0]count;

initial 
begin
count=3'b000;
y<=1'b0;
end

always@(posedge clk) begin

if(reset) 
	y<=1'b0;
	
else  

	begin
	
	if(count<3'b111) begin
		y<=1'b0;
		count<=count+1'b1;
		end
	else 
		y<=a;
		
		
		
	end

	
end
endmodule

full_adder.v

module full_adder(a,b,cin,sum,cout);
input a;
input b;
input cin;
output sum;
output cout;


assign sum=a^b^cin;
assign cout=(a&b)|(b&cin)|(cin&a);

endmodule

piso.v


//data is getting loaded but not coming out//
//uptade---> working fine all bits are coming out properly

module piso (clk,reset,load,shift,d_in,d_out);
input clk;
input reset;
input load;
input shift;
input [3:0] d_in;
output reg d_out;

//integer i;
reg [3:0] mem;
reg [2:0] counter;
reg flag;

///synchronization is the funckin problem
/*initial begin
counter=3'b000;
end*/

always@(posedge clk) begin
	if(reset)
		mem<=4'b0000;
 	
 	if(!reset) begin
 	
		if(load) begin	//loading is working well	
			mem<=d_in; 
			
			end
		
		if(shift) begin
		
				if(counter!=3'b011) begin
				//d_out=mem[0]; 
				mem<=mem>>1'b1;
				flag<=1'b1;     //first shift then pull to out
				counter<=counter+1'b1;
					end
	
					
				else			
				counter<=3'b000;
					
			 end
			 
			 if(flag==1'b1) begin
					d_out<=mem[0];
				end
	end
	
	
				
end
endmodule


/*  *************************************************************************************************************************************************************
	(done)data is getting loaded and shifted in mem accordingly 
	(should work out)but is taken out in the next cycle and given to full adder correspondingly- can be solved 
	(Done)But cin right from the first cycle is shown x  problem to be solved first.

*/

serial_adder.v
// A 4 bit serial adder

`include "full_adder.v"
`include "piso.v"
`include "single_shift.v"
`include "sipo.v"

module serial_adder(clk,load,reset,shift,a,b,sum);
input clk;
input load;
input shift;
input reset;
input [3:0]a;
input [3:0]b;
output [3:0]sum;


wire w1;
wire w2;
wire w3;
wire w4;
wire w5;

//module instantiations
piso p1 (.clk(clk),.reset(reset),.load(load),.shift(shift),.d_in(a),.d_out(w1));
piso p2 (.clk(clk),.reset(reset),.load(load),.shift(shift),.d_in(b),.d_out(w2));
full_adder f1 (.a(w1),.b(w2),.cin(w4),.sum(w5),.cout(w3));
single_shift s1(.clk(clk),.reset(reset),.shift(shift),.load(load),.a(w3),.y(w4));
sipo sp1 (.clk(clk),.reset(reset),.shift(shift),.a(w5),.out(sum));

endmodule

serial_adder_tb.v

//`include "serial_adder.v"
//test bench in verilog only for simulation level of verification 
module serial_adder_tb();
reg clk;
reg reset;
reg load;
reg shift;
reg [3:0]a;
reg [3:0]b;
wire [3:0]sum;

serial_adder dut(.clk(clk),.reset(reset),.load(load),.shift(shift),.a(a),.b(b),.sum(sum));

initial begin
$dumpfile("output_wave.vcd");
$dumpvars(0,serial_adder_tb);
end

initial begin

clk=1'b1;
reset=1'b1;
//load=1'b1;
//shift=1'b1;

#20
reset=1'b0;
load=1'b1;
shift=1'b1;

#20
a=4'b0101;
b=4'b0101;

#500 $finish;
end

always #5 clk=~clk;

endmodule

output_wave.vcd
$date
	Sun May 19 13:31:11 2024
$end
$version
	Icarus Verilog
$end
$timescale
	1s
$end
$scope module serial_adder_tb $end
$var wire 4 ! sum [3:0] $end
$var reg 4 " a [3:0] $end
$var reg 4 # b [3:0] $end
$var reg 1 $ clk $end
$var reg 1 % load $end
$var reg 1 & reset $end
$var reg 1 ' shift $end
$scope module dut $end
$var wire 4 ( a [3:0] $end
$var wire 4 ) b [3:0] $end
$var wire 1 $ clk $end
$var wire 1 % load $end
$var wire 1 & reset $end
$var wire 1 ' shift $end
$var wire 1 * w5 $end
$var wire 1 + w4 $end
$var wire 1 , w3 $end
$var wire 1 - w2 $end
$var wire 1 . w1 $end
$var wire 4 / sum [3:0] $end
$scope module f1 $end
$var wire 1 , cout $end
$var wire 1 * sum $end
$var wire 1 + cin $end
$var wire 1 - b $end
$var wire 1 . a $end
$upscope $end
$scope module p1 $end
$var wire 1 $ clk $end
$var wire 4 0 d_in [3:0] $end
$var wire 1 % load $end
$var wire 1 & reset $end
$var wire 1 ' shift $end
$var reg 3 1 counter [2:0] $end
$var reg 1 . d_out $end
$var reg 1 2 flag $end
$var reg 4 3 mem [3:0] $end
$upscope $end
$scope module p2 $end
$var wire 1 $ clk $end
$var wire 4 4 d_in [3:0] $end
$var wire 1 % load $end
$var wire 1 & reset $end
$var wire 1 ' shift $end
$var reg 3 5 counter [2:0] $end
$var reg 1 - d_out $end
$var reg 1 6 flag $end
$var reg 4 7 mem [3:0] $end
$upscope $end
$scope module s1 $end
$var wire 1 , a $end
$var wire 1 $ clk $end
$var wire 1 % load $end
$var wire 1 & reset $end
$var wire 1 ' shift $end
$var reg 3 8 count [2:0] $end
$var reg 1 + y $end
$upscope $end
$scope module sp1 $end
$var wire 1 * a $end
$var wire 1 $ clk $end
$var wire 1 & reset $end
$var wire 1 ' shift $end
$var reg 3 9 counter [2:0] $end
$var reg 4 : mem [3:0] $end
$var reg 4 ; out [3:0] $end
$upscope $end
$upscope $end
$upscope $end
$enddefinitions $end
#0
$dumpvars
bx ;
b0 :
bx 9
b0 8
b0 7
x6
bx 5
bx 4
b0 3
x2
bx 1
bx 0
bx /
x.
x-
x,
0+
x*
bx )
bx (
x'
1&
x%
1$
bx #
bx "
bx !
$end
#5
0$
#10
1$
#15
0$
#20
b0 1
bx 3
b0 5
bx 7
b1 8
b0 !
b0 /
b0 ;
b0 9
1$
1'
1%
0&
#25
0$
#30
b1 9
bx000 :
b10 8
b1 5
16
b0xxx 7
b1 1
12
b0xxx 3
1$
#35
0$
#40
b10 1
b0xx 3
b10 5
b0xx 7
b11 8
b10 9
bx00 :
1$
b101 #
b101 )
b101 4
b101 "
b101 (
b101 0
#45
0$
#50
b11 9
b100 8
b11 5
b0x 7
b11 1
b0x 3
bx0 :
1$
#55
0$
#60
b0 1
b101 3
b0 5
b101 7
b101 8
b100 9
bx :
1$
#65
0$
#70
1,
0*
bx !
bx /
bx ;
b0 9
b110 8
1-
b1 5
b10 7
1.
b1 1
b10 3
1$
#75
0$
#80
0,
0.
b10 1
b1 3
0-
b10 5
b1 7
b111 8
b0 !
b0 /
b0 ;
b1 9
b0xxx :
1$
#85
0$
#90
1,
b10 9
1-
b11 5
b0 7
1.
b11 1
b0 3
b0xx :
1$
#95
0$
#100
0,
1*
0.
b0 1
b101 3
0-
b0 5
b101 7
1+
b11 9
b0x :
1$
#105
0$
#110
1,
0*
b100 9
0+
1-
b1 5
b10 7
1.
b1 1
b10 3
b1000 :
1$
#115
0$
#120
0,
1*
0.
b10 1
b1 3
0-
b10 5
b1 7
1+
b1000 !
b1000 /
b1000 ;
b0 9
1$
#125
0$
#130
1,
0*
b0 !
b0 /
b0 ;
b1 9
0+
1-
b11 5
b0 7
1.
b11 1
b0 3
b1100 :
1$
#135
0$
#140
0,
1*
0.
b0 1
b101 3
0-
b0 5
b101 7
1+
b10 9
b110 :
1$
#145
0$
#150
1,
0*
b11 9
0+
1-
b1 5
b10 7
1.
b1 1
b10 3
b1011 :
1$
#155
0$
#160
0,
1*
0.
b10 1
b1 3
0-
b10 5
b1 7
1+
b100 9
b101 :
1$
#165
0$
#170
1,
0*
b101 !
b101 /
b101 ;
b0 9
0+
1-
b11 5
b0 7
1.
b11 1
b0 3
1$
#175
0$
#180
0,
1*
0.
b0 1
b101 3
0-
b0 5
b101 7
1+
b0 !
b0 /
b0 ;
b1 9
b10 :
1$
#185
0$
#190
1,
0*
b10 9
0+
1-
b1 5
b10 7
1.
b1 1
b10 3
b1001 :
1$
#195
0$
#200
0,
1*
0.
b10 1
b1 3
0-
b10 5
b1 7
1+
b11 9
b100 :
1$
#205
0$
#210
1,
0*
b100 9
0+
1-
b11 5
b0 7
1.
b11 1
b0 3
b1010 :
1$
#215
0$
#220
0,
1*
0.
b0 1
b101 3
0-
b0 5
b101 7
1+
b1010 !
b1010 /
b1010 ;
b0 9
1$
#225
0$
#230
1,
0*
b0 !
b0 /
b0 ;
b1 9
0+
1-
b1 5
b10 7
1.
b1 1
b10 3
b1101 :
1$
#235
0$
#240
0,
1*
0.
b10 1
b1 3
0-
b10 5
b1 7
1+
b10 9
b110 :
1$
#245
0$
#250
1,
0*
b11 9
0+
1-
b11 5
b0 7
1.
b11 1
b0 3
b1011 :
1$
#255
0$
#260
0,
1*
0.
b0 1
b101 3
0-
b0 5
b101 7
1+
b100 9
b101 :
1$
#265
0$
#270
1,
0*
b101 !
b101 /
b101 ;
b0 9
0+
1-
b1 5
b10 7
1.
b1 1
b10 3
1$
#275
0$
#280
0,
1*
0.
b10 1
b1 3
0-
b10 5
b1 7
1+
b0 !
b0 /
b0 ;
b1 9
b10 :
1$
#285
0$
#290
1,
0*
b10 9
0+
1-
b11 5
b0 7
1.
b11 1
b0 3
b1001 :
1$
#295
0$
#300
0,
1*
0.
b0 1
b101 3
0-
b0 5
b101 7
1+
b11 9
b100 :
1$
#305
0$
#310
1,
0*
b100 9
0+
1-
b1 5
b10 7
1.
b1 1
b10 3
b1010 :
1$
#315
0$
#320
0,
1*
0.
b10 1
b1 3
0-
b10 5
b1 7
1+
b1010 !
b1010 /
b1010 ;
b0 9
1$
#325
0$
#330
1,
0*
b0 !
b0 /
b0 ;
b1 9
0+
1-
b11 5
b0 7
1.
b11 1
b0 3
b1101 :
1$
#335
0$
#340
0,
1*
0.
b0 1
b101 3
0-
b0 5
b101 7
1+
b10 9
b110 :
1$
#345
0$
#350
1,
0*
b11 9
0+
1-
b1 5
b10 7
1.
b1 1
b10 3
b1011 :
1$
#355
0$
#360
0,
1*
0.
b10 1
b1 3
0-
b10 5
b1 7
1+
b100 9
b101 :
1$
#365
0$
#370
1,
0*
b101 !
b101 /
b101 ;
b0 9
0+
1-
b11 5
b0 7
1.
b11 1
b0 3
1$
#375
0$
#380
0,
1*
0.
b0 1
b101 3
0-
b0 5
b101 7
1+
b0 !
b0 /
b0 ;
b1 9
b10 :
1$
#385
0$
#390
1,
0*
b10 9
0+
1-
b1 5
b10 7
1.
b1 1
b10 3
b1001 :
1$
#395
0$
#400
0,
1*
0.
b10 1
b1 3
0-
b10 5
b1 7
1+
b11 9
b100 :
1$
#405
0$
#410
1,
0*
b100 9
0+
1-
b11 5
b0 7
1.
b11 1
b0 3
b1010 :
1$
#415
0$
#420
0,
1*
0.
b0 1
b101 3
0-
b0 5
b101 7
1+
b1010 !
b1010 /
b1010 ;
b0 9
1$
#425
0$
#430
1,
0*
b0 !
b0 /
b0 ;
b1 9
0+
1-
b1 5
b10 7
1.
b1 1
b10 3
b1101 :
1$
#435
0$
#440
0,
1*
0.
b10 1
b1 3
0-
b10 5
b1 7
1+
b10 9
b110 :
1$
#445
0$
#450
1,
0*
b11 9
0+
1-
b11 5
b0 7
1.
b11 1
b0 3
b1011 :
1$
#455
0$
#460
0,
1*
0.
b0 1
b101 3
0-
b0 5
b101 7
1+
b100 9
b101 :
1$
#465
0$
#470
1,
0*
b101 !
b101 /
b101 ;
b0 9
0+
1-
b1 5
b10 7
1.
b1 1
b10 3
1$
#475
0$
#480
0,
1*
0.
b10 1
b1 3
0-
b10 5
b1 7
1+
b0 !
b0 /
b0 ;
b1 9
b10 :
1$
#485
0$
#490
1,
0*
b10 9
0+
1-
b11 5
b0 7
1.
b11 1
b0 3
b1001 :
1$
#495
0$
#500
0,
1*
0.
b0 1
b101 3
0-
b0 5
b101 7
1+
b11 9
b100 :
1$
#505
0$
#510
1,
0*
b100 9
0+
1-
b1 5
b10 7
1.
b1 1
b10 3
b1010 :
1$
#515
0$
#520
0,
1*
0.
b10 1
b1 3
0-
b10 5
b1 7
1+
b1010 !
b1010 /
b1010 ;
b0 9
1$
#525
0$
#530
1,
0*
b0 !
b0 /
b0 ;
b1 9
0+
1-
b11 5
b0 7
1.
b11 1
b0 3
b1101 :
1$
#535
0$
#540
0,
1*
0.
b0 1
b101 3
0-
b0 5
b101 7
1+
b10 9
b110 :
1$
